gcpmate/__init__.py
gcpmate/gcpmate.py
gcpmate-1.0.2.dist-info/LICENSE
gcpmate-1.0.2.dist-info/METADATA
gcpmate-1.0.2.dist-info/WHEEL
gcpmate-1.0.2.dist-info/entry_points.txt
gcpmate-1.0.2.dist-info/top_level.txt
gcpmate-1.0.2.dist-info/RECORD
