Metadata-Version: 2.1
Name: gcpmate
Version: 1.0.2
Summary: An OpenAI-powered assistant for managing Google Cloud Platform resources.
Home-page: https://github.com/ontaptom/gcpmate
Author: Tomek Porozynski
Author-email: tomasz.porozynski@gmail.com
Classifier: Programming Language :: Python :: 3
Classifier: License :: OSI Approved :: Apache Software License
Classifier: Operating System :: POSIX :: Linux
License-File: LICENSE
Requires-Dist: openai (~=1.1.1)
Requires-Dist: prettytable (~=3.6.0)
